odoo/addons/oca_event_badge/README.rst
odoo/addons/oca_event_badge/__init__.py
odoo/addons/oca_event_badge/__manifest__.py
odoo/addons/oca_event_badge/readme/CONTRIBUTORS.rst
odoo/addons/oca_event_badge/readme/CREDITS.rst
odoo/addons/oca_event_badge/readme/DESCRIPTION.rst
odoo/addons/oca_event_badge/readme/USAGE.rst
odoo/addons/oca_event_badge/static/description/icon.png
odoo/addons/oca_event_badge/static/description/index.html
odoo/addons/oca_event_badge/static/src/css/event_event_template.scss
odoo/addons/oca_event_badge/static/src/img/oca_board.png
odoo/addons/oca_event_badge/static/src/img/oca_delegate.png
odoo/addons/oca_event_badge/static/src/img/oca_member.png
odoo/addons/oca_event_badge/views/event_event_template_asset_report.xml
odoo/addons/oca_event_badge/views/event_event_templates.xml
odoo12_addon_oca_event_badge-12.0.1.0.0.99.dev3.dist-info/METADATA
odoo12_addon_oca_event_badge-12.0.1.0.0.99.dev3.dist-info/WHEEL
odoo12_addon_oca_event_badge-12.0.1.0.0.99.dev3.dist-info/top_level.txt
odoo12_addon_oca_event_badge-12.0.1.0.0.99.dev3.dist-info/RECORD
